README.md
setup.py
dta1.egg-info/PKG-INFO
dta1.egg-info/SOURCES.txt
dta1.egg-info/dependency_links.txt
dta1.egg-info/entry_points.txt
dta1.egg-info/namespace_packages.txt
dta1.egg-info/requires.txt
dta1.egg-info/top_level.txt
orangecontrib/__init__.py
orangecontrib/development_tools/__init__.py
orangecontrib/development_tools/widgets/Chatbot.py
orangecontrib/development_tools/widgets/MetManagement.py
orangecontrib/development_tools/widgets/VarManagement.py
orangecontrib/development_tools/widgets/WrapMessageBox.py
orangecontrib/development_tools/widgets/__init__.py
orangecontrib/development_tools/widgets/goto.py
orangecontrib/development_tools/widgets/shared_functions.py
orangecontrib/development_tools/widgets/shared_variables.py
orangecontrib/development_tools/widgets/subworkflow_input.py
orangecontrib/development_tools/widgets/dataset_devellopper/fake_input.csv
orangecontrib/development_tools/widgets/dataset_devellopper/fakeows.ows
orangecontrib/development_tools/widgets/dataset_devellopper/readme.txt
orangecontrib/development_tools/widgets/icons/Chatbot.svg
orangecontrib/development_tools/widgets/icons/DocumentEater.svg
orangecontrib/development_tools/widgets/icons/Embeddings.svg
orangecontrib/development_tools/widgets/icons/LanguageModel.svg
orangecontrib/development_tools/widgets/icons/Logo_HKH.svg
orangecontrib/development_tools/widgets/icons/TextPreprocessing.svg
orangecontrib/development_tools/widgets/icons/file-transfer.png
orangecontrib/development_tools/widgets/icons/goto.png
orangecontrib/development_tools/widgets/icons/input.png
orangecontrib/development_tools/widgets/icons/jcm_open_file_resize_alpha_channel.png
orangecontrib/development_tools/widgets/icons/output.png
orangecontrib/development_tools/widgets/icons/subworkflow_output.png
orangecontrib/development_tools/widgets/icons/tool.png
orangecontrib/development_tools/widgets/kernel_function/Table_management.py
orangecontrib/development_tools/widgets/kernel_function/Utils_box.py
orangecontrib/development_tools/widgets/widget_designer/goto.ui
orangecontrib/development_tools/widgets/widget_designer/load_tab.ui
orangecontrib/development_tools/widgets/widget_designer/orange_sub_workflow.ui
